MANIFEST.in
README.txt
setup.cfg
setup.py
docs/HISTORY.txt
docs/INSTALL.txt
docs/LICENSE.GPL
docs/LICENSE.txt
enpraxis/__init__.py
enpraxis.wordpressexchange.egg-info/PKG-INFO
enpraxis.wordpressexchange.egg-info/SOURCES.txt
enpraxis.wordpressexchange.egg-info/dependency_links.txt
enpraxis.wordpressexchange.egg-info/entry_points.txt
enpraxis.wordpressexchange.egg-info/namespace_packages.txt
enpraxis.wordpressexchange.egg-info/not-zip-safe
enpraxis.wordpressexchange.egg-info/requires.txt
enpraxis.wordpressexchange.egg-info/top_level.txt
enpraxis/wordpressexchange/HISTORY.txt
enpraxis/wordpressexchange/LICENSE.txt
enpraxis/wordpressexchange/__init__.py
enpraxis/wordpressexchange/config.py
enpraxis/wordpressexchange/configure.zcml
enpraxis/wordpressexchange/refresh.txt
enpraxis/wordpressexchange/version.txt
enpraxis/wordpressexchange/browser/__init__.py
enpraxis/wordpressexchange/browser/configure.zcml
enpraxis/wordpressexchange/browser/interfaces.py
enpraxis/wordpressexchange/browser/wordpresslib.py
enpraxis/wordpressexchange/browser/wpexportform.py
enpraxis/wordpressexchange/browser/wpimportform.py
enpraxis/wordpressexchange/docs/about.html
enpraxis/wordpressexchange/docs/web.css
enpraxis/wordpressexchange/docs/images/install_wordpressexchange.png
enpraxis/wordpressexchange/docs/images/wpexport_form.png
enpraxis/wordpressexchange/docs/images/wpicon.png
enpraxis/wordpressexchange/docs/images/wpimport_form.png
enpraxis/wordpressexchange/docs/src/ABOUT.rst
enpraxis/wordpressexchange/locales/wordpressexchange.pot
enpraxis/wordpressexchange/locales/af/LC_MESSAGES/wordpressexchange.mo
enpraxis/wordpressexchange/locales/af/LC_MESSAGES/wordpressexchange.po
enpraxis/wordpressexchange/locales/ar/LC_MESSAGES/wordpressexchange.mo
enpraxis/wordpressexchange/locales/ar/LC_MESSAGES/wordpressexchange.po
enpraxis/wordpressexchange/locales/bn/LC_MESSAGES/wordpressexchange.mo
enpraxis/wordpressexchange/locales/bn/LC_MESSAGES/wordpressexchange.po
enpraxis/wordpressexchange/locales/ca/LC_MESSAGES/wordpressexchange.mo
enpraxis/wordpressexchange/locales/ca/LC_MESSAGES/wordpressexchange.po
enpraxis/wordpressexchange/locales/de/LC_MESSAGES/wordpressexchange.mo
enpraxis/wordpressexchange/locales/de/LC_MESSAGES/wordpressexchange.po
enpraxis/wordpressexchange/locales/en/LC_MESSAGES/wordpressexchange.mo
enpraxis/wordpressexchange/locales/en/LC_MESSAGES/wordpressexchange.po
