Metadata-Version: 1.0
Name: enpraxis.wordpressexchange
Version: 1.2
Summary: A product that allows for import and export to and from a WordPress blog
Home-page: http://enpraxis.net/projects/eduCommons32/browser/enpraxis.wordpressexchange/
Author: enPraxis, LLC
Author-email: info@enpraxis.net
License: GPL
Keywords: WordPress import export
Platform: UNKNOWN
Classifier: Framework :: Plone
Classifier: Programming Language :: Python
Classifier: Topic :: Software Development :: Libraries :: Python Modules
